fastapi_request_limit/__init__.py
fastapi_request_limit/main.py
fastapi_request_limit-0.1.4.dist-info/METADATA
fastapi_request_limit-0.1.4.dist-info/WHEEL
fastapi_request_limit-0.1.4.dist-info/top_level.txt
fastapi_request_limit-0.1.4.dist-info/RECORD
