Metadata-Version: 2.1
Name: fastapi-request-limit
Version: 0.1.4
Summary: A FastAPI decorator for rate limiting requests based on specified parameters.
Home-page: https://github.com/sqot0/fastapi-request-limit
Author: Sqot0
Author-email: kuvshinov556@gmail.com
Classifier: Programming Language :: Python :: 3
Classifier: License :: OSI Approved :: MIT License
Classifier: Operating System :: OS Independent
Requires-Python: >=3.7
Requires-Dist: fastapi
